decisiontree_table_converter/__init__.py
decisiontree_table_converter/converter.py
Decisiontree_Table_Converter-0.1.2.dist-info/METADATA
Decisiontree_Table_Converter-0.1.2.dist-info/WHEEL
Decisiontree_Table_Converter-0.1.2.dist-info/top_level.txt
Decisiontree_Table_Converter-0.1.2.dist-info/RECORD
